sagemaker_gen_ai_jupyterlab_extension/__init__.py
sagemaker_gen_ai_jupyterlab_extension/_version.py
sagemaker_gen_ai_jupyterlab_extension/cancellation_token.py
sagemaker_gen_ai_jupyterlab_extension/constants.py
sagemaker_gen_ai_jupyterlab_extension/credential_manager.py
sagemaker_gen_ai_jupyterlab_extension/extract_utils.py
sagemaker_gen_ai_jupyterlab_extension/file_watcher.py
sagemaker_gen_ai_jupyterlab_extension/handlers.py
sagemaker_gen_ai_jupyterlab_extension/lsp_server_connection.py
sagemaker_gen_ai_jupyterlab_extension/q_customization.py
sagemaker_gen_ai_jupyterlab_extension/request_logger.py
sagemaker_gen_ai_jupyterlab_extension/telemetry_collector.py
sagemaker_gen_ai_jupyterlab_extension/websocket_handler.py
sagemaker_gen_ai_jupyterlab_extension/websocket_manager.py
sagemaker_gen_ai_jupyterlab_extension/labextension/build_log.json
sagemaker_gen_ai_jupyterlab_extension/labextension/package.json
sagemaker_gen_ai_jupyterlab_extension/labextension/schemas/@amzn/sagemaker_gen_ai_jupyterlab_extension/package.json.orig
sagemaker_gen_ai_jupyterlab_extension/labextension/schemas/@amzn/sagemaker_gen_ai_jupyterlab_extension/plugin.json
sagemaker_gen_ai_jupyterlab_extension/labextension/static/lib_index_js.970a625f07162b2e1f1c.js
sagemaker_gen_ai_jupyterlab_extension/labextension/static/lib_index_js.970a625f07162b2e1f1c.js.map
sagemaker_gen_ai_jupyterlab_extension/labextension/static/node_modules_wildcard-match_build_index_es_mjs.6054faa250f4a6c6cda3.js
sagemaker_gen_ai_jupyterlab_extension/labextension/static/node_modules_wildcard-match_build_index_es_mjs.6054faa250f4a6c6cda3.js.map
sagemaker_gen_ai_jupyterlab_extension/labextension/static/remoteEntry.07732cfbf68c7d74e735.js
sagemaker_gen_ai_jupyterlab_extension/labextension/static/remoteEntry.07732cfbf68c7d74e735.js.map
sagemaker_gen_ai_jupyterlab_extension/labextension/static/style.js
sagemaker_gen_ai_jupyterlab_extension/labextension/static/style_index_js.2c7139f8dd7575f410ce.js
sagemaker_gen_ai_jupyterlab_extension-1.0.12.dist-info/METADATA
sagemaker_gen_ai_jupyterlab_extension-1.0.12.dist-info/WHEEL
sagemaker_gen_ai_jupyterlab_extension-1.0.12.dist-info/licenses/LICENSE
sagemaker_gen_ai_jupyterlab_extension-1.0.12.dist-info/RECORD
