Metadata-Version: 2.4
Name: sagemaker_gen_ai_jupyterlab_extension
Version: 1.0.12
Dynamic: Author
Dynamic: Author-email
Dynamic: Keywords
Dynamic: Project-URL
Summary: An extension supporting SageMaker's GenAI capabilities in JupyterLab
License-File: LICENSE
Classifier: Framework :: Jupyter
Classifier: Framework :: Jupyter :: JupyterLab
Classifier: Framework :: Jupyter :: JupyterLab :: 4
Classifier: Framework :: Jupyter :: JupyterLab :: Extensions
Classifier: Framework :: Jupyter :: JupyterLab :: Extensions :: Prebuilt
Classifier: License :: OSI Approved :: BSD License
Classifier: Programming Language :: Python
Classifier: Programming Language :: Python :: 3
Classifier: Programming Language :: Python :: 3.7
Classifier: Programming Language :: Python :: 3.8
Classifier: Programming Language :: Python :: 3.9
Classifier: Programming Language :: Python :: 3.10
Classifier: Programming Language :: Python :: 3.11
Requires-Python: >=3.8
Requires-Dist: aws-embedded-metrics
Requires-Dist: jupyter-docprovider<3,>=1
Requires-Dist: jupyter-server-ydoc<3,>=1
Requires-Dist: requests>=2.25.0
Requires-Dist: sagemaker-jupyterlab-extension-common
Requires-Dist: watchdog>=2.1.0
